{
  "version": 3,
  "cmakeMinimumRequired": {
    "major": 3,
    "minor": 21,
    "patch": 0
  },
  "configurePresets": [
    {
      "name": "default",
      "displayName": "Emscripten",
      "binaryDir": "cmake-build",
      "generator": "Unix Makefiles",
      "cacheVariables": {
        "CMAKE_BUILD_TYPE": "Debug"
      },
      "toolchainFile": "$env{EMSDK}/upstream/emscripten/cmake/Modules/Platform/Emscripten.cmake"
    }
  ],
  "buildPresets": [
    {
      "name": "Debug",
      "configurePreset": "default",
      "configuration": "Debug"
    },
    {
      "name": "Release",
      "configurePreset": "default",
      "configuration": "Release"
    }
  ]
}
